{
	"info": {
		"_postman_id": "e65ae795-41f4-45bd-a3ca-46569a14a67c",
		"name": "HESP",
		"schema": "https://schema.getpostman.com/json/collection/v2.1.0/collection.json",
		"_exporter_id": "24015331"
	},
	"item": [
		{
			"name": "HE",
			"item": [
				{
					"name": "PUT - Update HE",
					"request": {
						"method": "PUT",
						"header": [],
						"body": {
							"mode": "raw",
							"raw": "{\n \"userId\": 3\n}\n"
						},
						"url": {
							"raw": "http://localhost:3000/api/he/8",
							"protocol": "http",
							"host": [
								"localhost"
							],
							"port": "3000",
							"path": [
								"api",
								"he",
								"8"
							]
						}
					},
					"response": []
				},
				{
					"name": "GET - 1 HE",
					"protocolProfileBehavior": {
						"disableBodyPruning": true
					},
					"request": {
						"method": "GET",
						"header": [],
						"body": {
							"mode": "raw",
							"raw": "{\n \"userId\": 3\n}\n"
						},
						"url": {
							"raw": "http://localhost:3000/api/he/8",
							"protocol": "http",
							"host": [
								"localhost"
							],
							"port": "3000",
							"path": [
								"api",
								"he",
								"8"
							]
						}
					},
					"response": []
				},
				{
					"name": "GET - All HE",
					"protocolProfileBehavior": {
						"disableBodyPruning": true
					},
					"request": {
						"method": "GET",
						"header": [],
						"body": {
							"mode": "raw",
							"raw": "{\n \"userId\": 3\n}\n"
						},
						"url": {
							"raw": "http://localhost:3000/api/he/he",
							"protocol": "http",
							"host": [
								"localhost"
							],
							"port": "3000",
							"path": [
								"api",
								"he",
								"he"
							]
						}
					},
					"response": []
				},
				{
					"name": "POST - HE",
					"request": {
						"method": "POST",
						"header": [],
						"body": {
							"mode": "raw",
							"raw": "{\n  \"firstName\": \"John\",\n  \"lastName\": \"Doe\",\n  \"email\": \"john.doe@example.com\",\n  \"phone\": \"+1 (123) 456-7890\",\n  \"registerNumber\": \"RN123456\"\n}\n"
						},
						"url": {
							"raw": "http://localhost:3000/api/he/he",
							"protocol": "http",
							"host": [
								"localhost"
							],
							"port": "3000",
							"path": [
								"api",
								"he",
								"he"
							]
						}
					},
					"response": []
				}
			]
		},
		{
			"name": "Staff",
			"item": [
				{
					"name": "PUT - Update Staff",
					"request": {
						"method": "PUT",
						"header": [],
						"body": {
							"mode": "raw",
							"raw": "{\n \"firstName\": \"kristian\"\n}\n"
						},
						"url": {
							"raw": "http://localhost:3000/api/staff/1",
							"protocol": "http",
							"host": [
								"localhost"
							],
							"port": "3000",
							"path": [
								"api",
								"staff",
								"1"
							]
						}
					},
					"response": []
				},
				{
					"name": "POST - Staff",
					"request": {
						"method": "POST",
						"header": [],
						"body": {
							"mode": "raw",
							"raw": "{\n    \"firstName\":\"arolddddeus\",\n    \"lastName\": \"test1dd23\"\n}",
							"options": {
								"raw": {
									"language": "json"
								}
							}
						},
						"url": {
							"raw": "http://localhost:3000/api/staff/staff",
							"protocol": "http",
							"host": [
								"localhost"
							],
							"port": "3000",
							"path": [
								"api",
								"staff",
								"staff"
							]
						}
					},
					"response": []
				},
				{
					"name": "GET - All Staff",
					"request": {
						"method": "GET",
						"header": [],
						"url": {
							"raw": "http://localhost:3000/api/staff/staff",
							"protocol": "http",
							"host": [
								"localhost"
							],
							"port": "3000",
							"path": [
								"api",
								"staff",
								"staff"
							]
						}
					},
					"response": []
				},
				{
					"name": "GET - 1 staff",
					"request": {
						"method": "GET",
						"header": [],
						"url": {
							"raw": "http://localhost:3000/api/staff/1",
							"protocol": "http",
							"host": [
								"localhost"
							],
							"port": "3000",
							"path": [
								"api",
								"staff",
								"1"
							]
						}
					},
					"response": []
				}
			]
		},
		{
			"name": "Comment",
			"item": [
				{
					"name": "POST - Comment",
					"request": {
						"method": "POST",
						"header": [],
						"body": {
							"mode": "raw",
							"raw": "{\n  \"message\": \"Sample message\",\n  \"relatedUser\": 8\n}\n",
							"options": {
								"raw": {
									"language": "json"
								}
							}
						},
						"url": {
							"raw": "http://localhost:3000/api/comments/comments",
							"protocol": "http",
							"host": [
								"localhost"
							],
							"port": "3000",
							"path": [
								"api",
								"comments",
								"comments"
							]
						}
					},
					"response": []
				},
				{
					"name": "GET - Comment",
					"request": {
						"method": "PUT",
						"header": [],
						"body": {
							"mode": "raw",
							"raw": "{\n        \"message\": \"hello from the other side\"\n\n}",
							"options": {
								"raw": {
									"language": "json"
								}
							}
						},
						"url": {
							"raw": "http://localhost:3000/api/comments/2",
							"protocol": "http",
							"host": [
								"localhost"
							],
							"port": "3000",
							"path": [
								"api",
								"comments",
								"2"
							]
						}
					},
					"response": []
				},
				{
					"name": "PUT - Update Comment Copy",
					"protocolProfileBehavior": {
						"disableBodyPruning": true
					},
					"request": {
						"method": "GET",
						"header": [],
						"body": {
							"mode": "raw",
							"raw": "{\n        \"message\": \"hello from the other side\"\n\n}",
							"options": {
								"raw": {
									"language": "json"
								}
							}
						},
						"url": {
							"raw": "http://localhost:3000/api/comments/2",
							"protocol": "http",
							"host": [
								"localhost"
							],
							"port": "3000",
							"path": [
								"api",
								"comments",
								"2"
							]
						}
					},
					"response": []
				},
				{
					"name": "GET - All comments",
					"protocolProfileBehavior": {
						"disableBodyPruning": true
					},
					"request": {
						"method": "GET",
						"header": [],
						"body": {
							"mode": "raw",
							"raw": "{\n    \"firstName\":\"arolddddeus\",\n    \"lastName\": \"test1dd23\"\n}",
							"options": {
								"raw": {
									"language": "json"
								}
							}
						},
						"url": {
							"raw": "http://localhost:3000/api/comments/comments",
							"protocol": "http",
							"host": [
								"localhost"
							],
							"port": "3000",
							"path": [
								"api",
								"comments",
								"comments"
							]
						}
					},
					"response": []
				}
			]
		},
		{
			"name": "wolcheck",
			"item": [
				{
					"name": "POST - WOL",
					"request": {
						"method": "POST",
						"header": [],
						"body": {
							"mode": "raw",
							"raw": "{\n\"health\": 1,\n\"work\": 3,\n\"finances\": 7,\n\"environment\": 4,\n\"love\": 9,\n\"familyFriends\": 8,\n\"personalDevelopment\": 6,\n\"fun\": 5,\n\"relatedUser\": 2\n}",
							"options": {
								"raw": {
									"language": "json"
								}
							}
						},
						"url": {
							"raw": "http://localhost:3000/api/wol/wol",
							"protocol": "http",
							"host": [
								"localhost"
							],
							"port": "3000",
							"path": [
								"api",
								"wol",
								"wol"
							]
						}
					},
					"response": []
				},
				{
					"name": "GET - 1 WOL",
					"protocolProfileBehavior": {
						"disableBodyPruning": true
					},
					"request": {
						"method": "GET",
						"header": [],
						"body": {
							"mode": "raw",
							"raw": "{\n    \"firstName\":\"arolddddeus\",\n    \"lastName\": \"test1dd23\"\n}",
							"options": {
								"raw": {
									"language": "json"
								}
							}
						},
						"url": {
							"raw": "http://localhost:3000/api/wol/2",
							"protocol": "http",
							"host": [
								"localhost"
							],
							"port": "3000",
							"path": [
								"api",
								"wol",
								"2"
							]
						}
					},
					"response": []
				},
				{
					"name": "PUT - Update WOL",
					"request": {
						"method": "PUT",
						"header": [],
						"body": {
							"mode": "raw",
							"raw": "{\n    \"love\": 10\n\n}",
							"options": {
								"raw": {
									"language": "json"
								}
							}
						},
						"url": {
							"raw": "http://localhost:3000/api/wol/2",
							"protocol": "http",
							"host": [
								"localhost"
							],
							"port": "3000",
							"path": [
								"api",
								"wol",
								"2"
							]
						}
					},
					"response": []
				},
				{
					"name": "GET - All WOL",
					"protocolProfileBehavior": {
						"disableBodyPruning": true
					},
					"request": {
						"method": "GET",
						"header": [],
						"body": {
							"mode": "raw",
							"raw": "{\n    \"firstName\":\"arolddddeus\",\n    \"lastName\": \"test1dd23\"\n}",
							"options": {
								"raw": {
									"language": "json"
								}
							}
						},
						"url": {
							"raw": "http://localhost:3000/api/wol/wol",
							"protocol": "http",
							"host": [
								"localhost"
							],
							"port": "3000",
							"path": [
								"api",
								"wol",
								"wol"
							]
						}
					},
					"response": []
				}
			]
		},
		{
			"name": "pdccheck",
			"item": [
				{
					"name": "POST - PDC",
					"request": {
						"method": "POST",
						"header": [],
						"body": {
							"mode": "raw",
							"raw": "{\n  \"trust\": 1,\n  \"willFollow\": 2,\n  \"retention\": 3,\n  \"commitment\": 4,\n  \"cv\": 5,\n  \"readyForInterviews\": 6,\n  \"advancement\": 7\n}\n",
							"options": {
								"raw": {
									"language": "json"
								}
							}
						},
						"url": {
							"raw": "http://localhost:3000/api/pdc/pdc",
							"protocol": "http",
							"host": [
								"localhost"
							],
							"port": "3000",
							"path": [
								"api",
								"pdc",
								"pdc"
							]
						}
					},
					"response": []
				},
				{
					"name": "PUT - PDC",
					"request": {
						"method": "PUT",
						"header": [],
						"body": {
							"mode": "raw",
							"raw": "{\n    \"cv\": 15\n}\n",
							"options": {
								"raw": {
									"language": "json"
								}
							}
						},
						"url": {
							"raw": "http://localhost:3000/api/pdc/5",
							"protocol": "http",
							"host": [
								"localhost"
							],
							"port": "3000",
							"path": [
								"api",
								"pdc",
								"5"
							]
						}
					},
					"response": []
				},
				{
					"name": "GET - All PDC",
					"protocolProfileBehavior": {
						"disableBodyPruning": true
					},
					"request": {
						"method": "GET",
						"header": [],
						"body": {
							"mode": "raw",
							"raw": "{\n  \"trust\": 1,\n  \"willFollow\": 2,\n  \"retention\": 3,\n  \"commitment\": 4,\n  \"cv\": 5,\n  \"readyForInterviews\": 6,\n  \"advancement\": 7\n}\n",
							"options": {
								"raw": {
									"language": "json"
								}
							}
						},
						"url": {
							"raw": "http://localhost:3000/api/pdc/pdc",
							"protocol": "http",
							"host": [
								"localhost"
							],
							"port": "3000",
							"path": [
								"api",
								"pdc",
								"pdc"
							]
						}
					},
					"response": []
				},
				{
					"name": "GET - 1 PDC",
					"protocolProfileBehavior": {
						"disableBodyPruning": true
					},
					"request": {
						"method": "GET",
						"header": [],
						"body": {
							"mode": "raw",
							"raw": "{\n  \"trust\": 1,\n  \"willFollow\": 2,\n  \"retention\": 3,\n  \"commitment\": 4,\n  \"cv\": 5,\n  \"readyForInterviews\": 6,\n  \"advancement\": 7\n}\n",
							"options": {
								"raw": {
									"language": "json"
								}
							}
						},
						"url": {
							"raw": "http://localhost:3000/api/pdc/5",
							"protocol": "http",
							"host": [
								"localhost"
							],
							"port": "3000",
							"path": [
								"api",
								"pdc",
								"5"
							]
						}
					},
					"response": []
				}
			]
		},
		{
			"name": "hedata",
			"item": []
		},
		{
			"name": "soloutions",
			"item": [
				{
					"name": "POST - Soloutions",
					"request": {
						"method": "POST",
						"header": [],
						"body": {
							"mode": "raw",
							"raw": "{\n    \"code\":\"checdk thisd out\"\n}",
							"options": {
								"raw": {
									"language": "json"
								}
							}
						},
						"url": {
							"raw": "http://localhost:3000/api/soloutions/soloutions",
							"protocol": "http",
							"host": [
								"localhost"
							],
							"port": "3000",
							"path": [
								"api",
								"soloutions",
								"soloutions"
							]
						}
					},
					"response": []
				},
				{
					"name": "GET - All Soloutions",
					"protocolProfileBehavior": {
						"disableBodyPruning": true
					},
					"request": {
						"method": "GET",
						"header": [],
						"body": {
							"mode": "raw",
							"raw": "{\n    \"firstName\":\"arolddddeus\",\n    \"lastName\": \"test1dd23\"\n}",
							"options": {
								"raw": {
									"language": "json"
								}
							}
						},
						"url": {
							"raw": "http://localhost:3000/api/soloutions/soloutions",
							"protocol": "http",
							"host": [
								"localhost"
							],
							"port": "3000",
							"path": [
								"api",
								"soloutions",
								"soloutions"
							]
						}
					},
					"response": []
				},
				{
					"name": "GET - 1 Soloution",
					"protocolProfileBehavior": {
						"disableBodyPruning": true
					},
					"request": {
						"method": "GET",
						"header": [],
						"body": {
							"mode": "raw",
							"raw": "{\n    \"firstName\":\"arolddddeus\",\n    \"lastName\": \"test1dd23\"\n}",
							"options": {
								"raw": {
									"language": "json"
								}
							}
						},
						"url": {
							"raw": "http://localhost:3000/api/soloutions/2",
							"protocol": "http",
							"host": [
								"localhost"
							],
							"port": "3000",
							"path": [
								"api",
								"soloutions",
								"2"
							]
						}
					},
					"response": []
				},
				{
					"name": "PUT - Update Soloutions",
					"request": {
						"method": "PUT",
						"header": [],
						"body": {
							"mode": "raw",
							"raw": "{\n    \"code\":\"this is updated\"\n}",
							"options": {
								"raw": {
									"language": "json"
								}
							}
						},
						"url": {
							"raw": "http://localhost:3000/api/soloutions/2",
							"protocol": "http",
							"host": [
								"localhost"
							],
							"port": "3000",
							"path": [
								"api",
								"soloutions",
								"2"
							]
						}
					},
					"response": []
				}
			]
		},
		{
			"name": "providedsoloutions",
			"item": []
		}
	]
}